local_attention_flax/__init__.py
local_attention_flax/local_attention_flax.py
local_attention_flax-0.0.2.dist-info/LICENSE
local_attention_flax-0.0.2.dist-info/METADATA
local_attention_flax-0.0.2.dist-info/WHEEL
local_attention_flax-0.0.2.dist-info/top_level.txt
local_attention_flax-0.0.2.dist-info/RECORD
