Metadata-Version: 2.1
Name: local-attention-flax
Version: 0.0.2
Summary: Local Attention - Flax Module in Jax
Home-page: https://github.com/lucidrains/local-attention-flax
Author: Phil Wang
Author-email: UNKNOWN
License: MIT
Keywords: artificial intelligence,deep learning,attention mechanism,jax
Platform: UNKNOWN
Classifier: Development Status :: 4 - Beta
Classifier: Intended Audience :: Developers
Classifier: Topic :: Scientific/Engineering :: Artificial Intelligence
Classifier: License :: OSI Approved :: MIT License
Classifier: Programming Language :: Python :: 3.6
Requires-Dist: einops (>=0.3)
Requires-Dist: flax
Requires-Dist: jax
Requires-Dist: jaxlib
